advanced_filters/__init__.py
advanced_filters/admin.py
advanced_filters/form_helpers.py
advanced_filters/forms.py
advanced_filters/mixins.py
advanced_filters/models.py
advanced_filters/q_serializer.py
advanced_filters/urls.py
advanced_filters/views.py
advanced_filters/migrations/0001_initial.py
advanced_filters/migrations/0002_advancedfilter_created_at.py
advanced_filters/migrations/0003_auto_20180610_0718.py
advanced_filters/migrations/__init__.py
advanced_filters/static/orig_inlines.js
advanced_filters/static/orig_inlines.min.js
advanced_filters/static/advanced-filters/advanced-filters.css
advanced_filters/static/advanced-filters/advanced-filters.js
advanced_filters/static/advanced-filters/jquery_adder.js
advanced_filters/static/magnific-popup/jquery.magnific-popup.js
advanced_filters/static/magnific-popup/magnific-popup-license.txt
advanced_filters/static/magnific-popup/magnific-popup.css
advanced_filters/static/select2/select2-spinner.gif
advanced_filters/static/select2/select2.min.css
advanced_filters/static/select2/select2.min.js
advanced_filters/static/select2/select2.png
advanced_filters/static/select2/select2x2.png
advanced_filters/templates/admin/advanced_filters.html
advanced_filters/templates/admin/common_js_init.html
advanced_filters/templates/admin/advanced_filters/change_form.html
django_advanced_filters-2.0.0.dist-info/LICENSE
django_advanced_filters-2.0.0.dist-info/METADATA
django_advanced_filters-2.0.0.dist-info/WHEEL
django_advanced_filters-2.0.0.dist-info/top_level.txt
django_advanced_filters-2.0.0.dist-info/RECORD
